{"Agafonov, V. V.": {"WOS": "Natl Univ Sci & Technol MISIS, Moscow, Russia"}, "Aletti, Giacomo": {"WOS": "Univ Milan, ADAMSS Ctr, Milan, Italy"}, "Almeida, Jonas S.": {"WOS": ""}, "Al-Zahrani, Fahad": {"WOS": "Umm Al Qura Univ, Mecca, Saudi Arabia"}, "Angeles Villa, Manuel": {"WOS": "Univ Autonoma Baja California Sur, Dept Acad Econ, La Paz, Mexico"}, "Arputharaj, Kannan": {"WOS": "Anna Univ, Dept Informat Sci & Technol, Coll Engn, Madras, Tamil Nadu, India"}, "Arunachalam, A. R.": {"WOS": "Dr MGR Univ, Dept CSE, Chennai, Tamil Nadu, India"}, "Bajwa, Hassan": {"WOS": "Univ Bridgeport, Dept Elect Engn, Bridgeport, CT 06604 USA"}, "Balasubramanian, Mahendran": {"WOS": "Univ Arkansas, Sch Human Environm Sci, Apparel Merchandising & Prod Dev, 118 Home Econ Bldg, Fayetteville, AR 72701 USA"}, "Balasundaram, A.": {"WOS": "Vellore Inst Technol VIT, Sch Comp Sci & Engn, Ctr Cyber Phys Syst, Chennai, Tamil Nadu, India"}, "Balasundaram, Sadhu Ramakrishnan": {"WOS": "Natl Inst Technol, Dept Comp Applicat, Tiruchirappalli 620015, Tamil Nadu, India"}, "Barberis, Dario": {"WOS": "Univ Genoa, Genoa, Italy"}, "Bauer, Denis C.": {"WOS": "CSIRO, Sydney, NSW 2052, Australia"}, "Bejarano-Luque, J. L.": {"WOS": "Univ Malaga, Dept Ingn Comunicac, Malaga 29010, Spain"}, "Benhlima, Laila": {"WOS": "Mohammed V Univ Rabat, Rabat, Morocco"}, "Beresewicz, Maciej": {"WOS": "Poznan Univ Econ & Business, Fac Informat & Elect Econ, Dept Stat, Al Niepodleglosci 10, PL-61875 Poznan, Poland"}, "Biswas, R.": {"WOS": "Tezpur Univ, Dept Phys, Tezpur 784028, Assam, India"}, "Bokhari, Syed Fawad": {"WOS": "Univ Lahore, Dept Mech Engn, Lahore, Pakistan"}, "Bolignano, Andrea": {"WOS": "ARPA Lazio, Via Garibaldi 114, I-02100 Rieti, Italy"}, "Bouamrane, Karim": {"WOS": "Univ Oran 1, Comp Sci Dept, Ahmed BENBELLA, Oran, Algeria"}, "Brantner, Matthias": {"WOS": "Oracle Labs, Lugano, Switzerland"}, "Burinskiene, Aurelija": {"WOS": "Vilnius Gediminas Tech Univ, Vilnius, Lithuania"}, "Calhoun, Vince D.": {"WOS": "Georgia Tech Univ, Dept Psychol, Atlanta, GA USA"}, "Cappiello, Giuseppe": {"WOS": "Univ Bologna, Dept Management, Via Capo Lucca 34, I-40126 Bologna, Italy"}, "Cerezo Gilarranz, Julio": {"WOS": ""}, "Chakkaravarthy, A. Prabhu": {"WOS": "St Josephs Coll Engn, Dept CSE, Chennai, Tamil Nadu, India"}, "Chang, Jae-Woo": {"WOS": "Agcy Def Dev, R&D Inst 1, Directorate 4, Daejeon, South Korea"}, "Chang, Yohan": {"WOS": "Korea Res Inst Human Settlements, KRIHS Data Lab, Sejong Si, South Korea"}, "Chaudhuri, Surajit": {"WOS": "Microsoft, Redmond, WA 98052 USA"}, "Chen, Mu-Yen": {"WOS": "Natl Cheng Kung Univ, Dept Engn Sci, Tainan 701, Taiwan"}, "Chen, Runsheng": {"WOS": "Chinese Acad Sci, Ctr Big Data Res Hlth, Inst Biophys, Key Lab RNA Biol, Beijing 100101, Peoples R China"}, "Chen, Wei": {"WOS": "Southern Med Univ, Affiliated Foshan Matern & Child Healthcare Hosp, Foshan Matern & Child Healthcare Hosp, Foshan 528000, Peoples R China"}, "Chesler, Elissa J.": {"WOS": "Univ Tennessee Knoxville, Knoxville, TN USA"}, "Chiu, Carter": {"WOS": "Univ Nevada, Dept Comp Sci, Las Vegas, NV 89154 USA"}, "Cho, Yongyun": {"WOS": "Soongsil Univ, Sch Comp Sci & Engn, Coll Informat Technol, Seoul, South Korea"}, "Choi, Jongmoo": {"WOS": "Samsung Semicond Inc, Memory Solut Lab, San Jose, CA 95134 USA"}, "Chung, Kyungyong": {"WOS": "Kyonggi Univ, Div Comp Sci & Engn, Suwon 16227, South Korea"}, "Chung, Yeh-Ching": {"WOS": "Natl Tsing Hua Univ, Dept Comp Sci, Hsinchu 300, Taiwan"}, "Chuvilina, Olesya V.": {"WOS": "Volga State Univ Water Transport, Dept Foreign Languages, Nesterov Str 5, Nizhnii Novgorod 603950, Russia"}, "Conti, Mauro": {"WOS": "Univ Padua, Dept Math, Padua, Italy"}, "Corneanu, Isabela": {"WOS": "SC RITMIC COM SRL Suceava, Suceava, Romania"}, "Cristea, Valentin": {"WOS": "Univ Politehn Bucuresti, Fac Automat Control & Comp, Bucharest, Romania"}, "da Silva, J. R. S. C.": {"WOS": "Sao Paulo State Univ Unesp, Dept Engn & Exact Sci, Jaboticabal, SP, Brazil"}, "Das, Pritishree": {"WOS": "Utkal Univ, Vani Vihar, Dept Psychol, Bhubaneswar, India"}, "Degen, Markus": {"WOS": "Peakmarks, Zurich, Switzerland"}, "Denaxas, Spiros": {"WOS": "Univ Med Ctr Utrecht, Julius Ctr Hlth Sci & Primary Care, Heidelberglaan 100, NL-3584 CX Utrecht, Netherlands"}, "Devendran, A.": {"WOS": "Dr MGR Educ & Res Inst, Madras, Tamil Nadu, India"}, "Dhavachelvan, P.": {"WOS": "Pondicherry Univ, Dept Comp Sci, Pondicherry, India"}, "Dilip, Golda": {"WOS": "SRM Inst Sci & Technol, Fac Comp Sci & Engn, Chennai, Tamil Nadu, India"}, "Ding, Hua": {"WOS": "Univ Electrocommun, Grad Sch Informat & Engn, Chofu, Tokyo, Japan"}, "Dopazo, Joaquin": {"WOS": "Genometra SL, Valencia, Spain"}, "Du, Xiaojiang": {"WOS": "Temple Univ, Dept Comp & Informat Sci, Philadelphia, PA 19122 USA"}, "Elayidom, Sudheep": {"WOS": "Cochin Univ Sci & Technol, Div Comp Sci, Kochi, Kerala, India"}, "Eldawy, Ahmed": {"WOS": "Univ Calif Riverside, Dept Comp Sci & Engn, Riverside, CA 92521 USA"}, "ElMahalawy, Ahmed": {"WOS": "Menoufia Univ, Fac Elect Engn, Al Minufya, Egypt"}, "El-Sayed, Ayman": {"WOS": "Menoufia Univ, Fac Elect Engn, Menoufia, Egypt"}, "El-Soudani, Magdy M. S.": {"WOS": "Cairo Univ, Elect & Elect Commun Dept, Fac Engn, Cairo 12613, Egypt"}, "Espejo, Raul": {"WOS": "Syncho Res, Lincoln, England"}, "Fabian, Martin": {"WOS": "Chalmers Univ Technol, Dept Elect Engn, S-41296 Gothenburg, Sweden"}, "Fan, Wentao": {"WOS": "Huaqiao Univ, Coll Comp Sci & Technol, Jimei AVE 668, Xiamen 361021, Peoples R China"}, "Fehm, T.": {"WOS": "Univ Klinikums Dusseldorf, Frauenklin, Forschungslab, Dusseldorf, Germany"}, "Fietkau, R.": {"WOS": "Univ Hosp Erlangen, Radiat Oncol, Erlangen, Germany"}, "Fromm, Davida": {"WOS": "Carnegie Mellon Univ, 5000 Forbes Ave, Pittsburgh, PA 15213 USA"}, "Fuad, Muztaba": {"WOS": "Winston Salem State Univ, Dept Comp Sci, Winston Salem, NC 27110 USA"}, "Gagliardo, Pablo": {"WOS": "FIVAN, Valencia, Spain"}, "Georgakopoulos, Dimitrios": {"WOS": "Swinburne Univ Technol, Hawthorn, Vic, Australia"}, "Ghosal, Prasun": {"WOS": "IIEST, Sibpur, India"}, "Graebel, Stefan": {"WOS": "Charite Univ Med Berlin, Klin Hals Nasen & Ohrenheilkunde CVK, Klin & Poliklin Hals Nasen Ohrenheilkunde CCM, Berlin, Germany"}, "Groth, Paul": {"WOS": "Elsevier Labs, NL-1043 NX Amsterdam, Netherlands"}, "Grunwald, Sabine": {"WOS": "Univ Florida, Soil & Water Sci Dept, Gainesville, FL 32611 USA"}, "Gugulothu, Narsimha": {"WOS": "JNTUH, Hyderabad, India"}, "Gunasekaran, Angappa": {"WOS": "Calif State Univ Bakersfield, Sch Business & Publ Adm, 9001 Stockdale Highway,20BDC-140, Bakersfield, CA 93311 USA"}, "Gupta, Sangeeta": {"WOS": "Vardhaman Coll Engn, Hyderabad, India"}, "Hair, Abdellatif": {"WOS": "Sultan Moulay Slimane Univ, Fac Sci & Technol, Beni Mellal, Morocco"}, "Hara, Takahiro": {"WOS": "Osaka Univ, Grad Sch Informat Sci & Technol, Dept Multimedia Engn, Osaka 5650871, Japan"}, "Harada, Mitsuru": {"WOS": "NTT Network Innovat Labs, Tokyo, Tokyo, Japan"}, "He, Shunmin": {"WOS": "Chinese Acad Sci, Adv Comp Res Ctr, Inst Comp Technol, Key Lab Intelligent Informat Proc,Bioinformat Res, Beijing 100190, Peoples R China"}, "Heo, Tae-Young": {"WOS": "Chungbuk Natl Univ, Dept Informat Stat, Cheongju, South Korea"}, "Herrera, Francisco": {"WOS": "Univ Granada, Dept Comp Sci & Artificial Intelligence, CITIC UGR Res Ctr Informat & Commun Technol, Granada, Spain"}, "Hong, Eui Kyeong": {"WOS": "Univ Seoul, Seoul, South Korea"}, "Hossain, M. Shamim": {"WOS": "Soochow Univ, Dept Math, Taipei, Taiwan"}, "Huang, Mao Lin": {"WOS": "Univ Technol Sydney, Fac Engn & IT, Sch Software, Sydney, NSW 2007, Australia"}, "Huang, Qian": {"WOS": "Wuchang Polytech Coll, Wuhan 430060, Hubei, Peoples R China"}, "Huang, Zhiwei": {"WOS": "Harvard Med Sch, Boston Childrens Hosp, Div Hematol Oncol, Boston, MA 02115 USA"}, "Hung, Patrick C. K.": {"WOS": "Univ Ontario Inst Technol, Fac Business & IT, Oshawa, ON, Canada"}, "Igarashi, Yasuhiko": {"WOS": "Univ Tsukuba, Fac Engn Informat & Syst, 1-1-1 Tennodai, Tsukuba, Ibaraki 3058573, Japan"}, "Inoguchi, Yasushi": {"WOS": "JAIST, Res Ctr Adv Comp Infrastruct, Nomi, Japan"}, "Ionescu, Sorin": {"WOS": "Univ Politehn Bucuresti, Ind Engn Dept, Bucharest, Romania"}, "Iosifidis, Spyridon": {"WOS": "Univ Aegean, Dept Environm, Biodivers Conservat Lab, Mitilini, Greece"}, "Iyer, Brijesh": {"WOS": "Dr BATU, Lonere, Maharashtra, India"}, "Jadi, Amr": {"WOS": "Univ Hail, Dept Comp Sci & Informat, Coll Comp Sci & Engn, Hail, Saudi Arabia"}, "Jeyanthi, N.": {"WOS": "VIT, Sch Informat Technol & Engn, Vellore, Tamil Nadu, India"}, "Jha, Shantenu": {"WOS": "Rutgers State Univ, RADICAL, ECE, Piscataway, NJ 08854 USA"}, "Jian, Wen-Shan": {"WOS": "Taipei Med Univ, Sch Hlth Care Adm, Taipei, Taiwan"}, "Jiang, Wei": {"WOS": "Harbin Med Univ, Coll Bioinformat Sci & Technol, Harbin 150081, Peoples R China"}, "Joshi, Rajendra": {"WOS": "Pirbright Inst, Ash Rd, Pirbright GU24 0NF, Surrey, England"}, "Kahappan, M.": {"WOS": "PSR Engn Coll, Dept Comp Sci & Engn, Sivakasi, Tamil Nadu, India"}, "Karapidakis, Emmanuel": {"WOS": "Adrestia Res & Dev PPC, GR-71202 Iraklion, Greece"}, "Karthik, S.": {"WOS": "SNS Coll Technol, Dept Comp Sci & Engn, Coimbatore, Tamil Nadu, India"}, "Kayarvizhy, N.": {"WOS": "BMS Coll Engn, Bengaluru, India"}, "Khan, Mohammad Aamir": {"WOS": "Univ Lahore, Fac Engn & Technol, Dept Mech Engn, Lahore, Pakistan"}, "Kim, Bum-Tae": {"WOS": "Soonchunhyang Univ, Dept Neurosurg, Bucheon Hosp, 170 Jomaru Ro, Bucheon 14584, South Korea"}, "Kim, Jeong-Joon": {"WOS": "Korea Polytech Univ, Dept Comp Sci & Engn, Shihung, South Korea"}, "Kim, S. -K.": {"WOS": "Catholic Univ, Daegu Sch Med, Dept Med Stat, Daegu, South Korea"}, "Kim, Seokhoon": {"WOS": "Soonchunhyang Univ, Dept Software Convergence, Asan 31538, South Korea"}, "Kim, T. W.": {"WOS": "Univ Ulsan, Asan Med Ctr, Oncol, Coll Med, Seoul, South Korea"}, "Kim, Yae-Jean": {"WOS": "Chungbuk Natl Univ Hosp, Dept Pediat, Cheongju, South Korea"}, "Kindrat, O. V.": {"WOS": "Lviv Polytech Natl Univ, Lvov, Ukraine"}, "Kistner, Bruno": {"WOS": "Porsche AG, Porschestr 911, D-71287 Weissach, Germany"}, "Klassen, Roman K.": {"WOS": "Kazan Natl Res Tech Univ, Kazan, Russia"}, "Ko, Young-Woong": {"WOS": "Hallym Univ, Dept Comp Engn, Chunchon 200702, Gangwon, South Korea"}, "Konrath, Sara": {"WOS": "Univ Michigan, Inst Social Res, Ann Arbor, MI 48104 USA"}, "Koo, Choongwan": {"WOS": "Incheon Natl Univ, Div Architecture & Urban Design, Incheon 22012, South Korea"}, "Kumar, Manish": {"WOS": "Indian Inst Informat Technol, Dept Informat Technol, Allahabad, Uttar Pradesh, India"}, "Kupriyanov, A. V.": {"WOS": "Samara Natl Res Univ, Moskovskoye Shosse 34, Samara 443086, Russia"}, "Kurtanjek, Zelimir": {"WOS": "Univ Zagreb, Dept Food Technol & Biotechnol, Zagreb, Croatia"}, "Kwon, Ji-Woong": {"WOS": "Natl Canc Ctr, Neurooncol Clin, Goyang, South Korea"}, "Lee, Il Woo": {"WOS": "Hallym Univ, Dept Stat, Chunchon, Gangwon, South Korea"}, "Lee, Jinyi": {"WOS": "Chosun Univ, IT Based Real Time NDT Ctr, Gwangju 61452, South Korea"}, "Lee, Tae Eun": {"WOS": "Jeonbuk Natl Univ, Med Sch, Dept Ophthalmol, Jeonju, South Korea"}, "Li, Guo-Ming": {"WOS": "Shanghai Jiao Tong Univ, Sch Mech Engn, Shanghai 200240, Peoples R China"}, "Li, Guozhong": {"WOS": "Kunming Univ Sci & Technol, Dept MSIS, 68 Wenchang Rd,121 St, Kunming 650093, Yunnan, Peoples R China"}, "Li, Xia_0": {"WOS": "Harbin Med Univ, Dept Neurol, Affiliated Hosp 2, Harbin 150081, Peoples R China"}, "Li, Xia_1": {"WOS": "Hainan Med Univ, Coll Biomed Informat & Engn, Hainan Women & Childrens Med Ctr, Key Lab Trop Translat Med,Minist Educ, Haikou 571199, Hainan, Peoples R China"}, "Li, Ye": {"WOS": "Silesian Tech Univ, Inst Math, Kaszubska 23, PL-44100 Gliwice, Poland"}, "Li, Yongsheng": {"WOS": "Hainan Med Univ, Hainan Women & Childrens Med Ctr, Coll Biomed Informat & Engn, Key Lab Trop Translat Med,Minist Educ, Haikou 571199, Hainan, Peoples R China"}, "Li, Zhixiong": {"WOS": "Univ Wollongong, Sch Mech Mat Mechatron & Biomed Engn, Wollongong, NSW 2522, Australia"}, "Liang, Wei": {"WOS": "Xiamen Univ Technol, Key Lab Internet Things Applicat Technol Fujian P, Xiamen, Peoples R China"}, "Lin, Bo-Yen": {"WOS": "Natl Chiao Tung Univ, Inst Elect, Hsinchu 300, Taiwan"}, "Lin, Chin-Yang": {"WOS": "Natl Chengchi Univ, Dept Comp Sci, Taipei, Taiwan"}, "Lingareddy, Sanjeev C.": {"WOS": "Sri Venketeshwara Coll Engn, Dept Comp Sci, Bangalore, Karnataka, India"}, "Linstead, Erik": {"WOS": "Chapman Univ, Schmid Coll Sci & Technol, Orange, CA 92866 USA"}, "Lisachenko, D. A.": {"WOS": "St Petersburg State Univ, Dept Gen Phys 2, St Petersburg, Russia"}, "Liu, Xiaomeng": {"WOS": "China Meteorol Adm, Training Ctr, Hebei Branch, Baoding 071000, Hebei, Peoples R China"}, "Lloret, Jaime": {"WOS": "Univ Politecn Valencia, Integrated Management Coastal Res Inst, E-46022 Valencia, Spain"}, "Lohi, Hannes": {"WOS": "Univ Colorado, Dept Comp Sci, Boulder, CO 80309 USA"}, "Macfarlane, Peter W.": {"WOS": "Univ Glasgow, Inst Hlth & Wellbeing, Glasgow, Lanark, Scotland"}, "Madani, Kurosh": {"WOS": "Univ Paris Est, LISSI EA 3956, Images Signals & Intelligent Syst Lab, Creteil, France"}, "Maizate, Abderrahim": {"WOS": "Univ Hassan 2, RITM ESTC, CED ENSEM, Casablanca, Morocco"}, "Majji, Sankararao": {"WOS": "GRIET, Hyderabad, India"}, "Makarenko, I. A.": {"WOS": "Sumy State Univ, Econ Sci, Sumy, Ukraine"}, "Meng, Zhao-Peng": {"WOS": "Tianjin Univ, Sch Comp Software, Tianjin 300072, Peoples R China"}, "Miguel Pla-Aragones, Lluis": {"WOS": "Univ Lleida, Dept Math, Lleida, Spain"}, "Mirzaei, Parham A.": {"WOS": "Univ Nottingham, Architecture & Built Environm Dept, Univ Pk, Nottingham NG 2RD, England"}, "Mohammed, Sabah": {"WOS": "Lakehead Univ, Dept Comp Sci, 955 Oliver Rd, Thunder Bay, ON P7B 5E1, Canada"}, "Motahari-Nezhad, Hamid Reza": {"WOS": "Univ New S Wales, Sch Comp Sci & Engn, Sydney, NSW, Australia"}, "Mukhopadhyay, Supratik": {"WOS": "Louisiana State Univ, 164 B Coates Hall, Baton Rouge, LA 70803 USA"}, "Nicolle, Christophe": {"WOS": "Univ Bourgogne Franche Comte, Dijon, France"}, "Nikolaevich, Tisenko Victor": {"WOS": "Peter Great St Petersburg Polytech Univ, Syst Automat Design, Polytech Skaya 29, St Petersburg, Russia"}, "O'Sullivan, Barry": {"WOS": "Univ Coll Cork, Dept Comp Sci, Cork Constraint Computat Ctr, Cork, Ireland"}, "Padhariya, Nilesh": {"WOS": "Shree M&N Virani Sci Coll, Dept Comp Sci, Rajkot, GJ, India"}, "Pakzad, Shamim N.": {"WOS": "Lehigh Univ, Dept Civil & Environm Engn, 117 ATLSS Dr, Bethlehem, PA 18015 USA"}, "Pallez, Guillaume": {"WOS": "INRIA, F-33405 Talence, France"}, "Panda, Bijaya Kumar": {"WOS": "Berhampur Univ, Berhampur, India"}, "Park, Jeong-Min": {"WOS": "Gangdong Coll, Gyeonggi Do, South Korea"}, "Park, Young-Ho": {"WOS": "Chungbuk Natl Univ, Dept Comp Sci, Chungbuk, South Korea"}, "Pasha, Urooj": {"WOS": "Bahauddin Zakariya Univ, Informat Technol, Multan, Pakistan"}, "Pasupathy, S.": {"WOS": "Annamalai Univ, Dept Comp Sci & Engn, Annamalainagar 608002, Tamil Nadu, India"}, "Pedrycz, Witold": {"WOS": "Univ Alberta, Dept Elect & Comp Engn, Edmonton, AB T6R 2V4, Canada"}, "Pepe, Guglielmina": {"WOS": "Univ Florence, Degenerat & Neoplast Dis Develop Novel Therapies, Ctr Excellence Study Mol & Clin Level Chron, Florence, Italy"}, "Priyadarsini, P. L. K.": {"WOS": "SASTRA Univ, Sch Comp, Thanjavur, Tamil Nadu, India"}, "Puliafito, Antonio": {"WOS": "Univ Messina, I-98122 Messina, Italy"}, "Pulist, S. K.": {"WOS": "Indira Gandhi Natl Open Univ, New Delhi, India"}, "Pushpa, S.": {"WOS": "St Peters Univ, Dept Comp Sci & Engn, Chennai, Tamil Nadu, India"}, "Qin, Xiao": {"WOS": "Auburn Univ, Dept Comp Sci & Software Engn, Auburn, AL 36849 USA"}, "Qualters, Irene": {"WOS": "Natl Sci Fdn, Comp & Informat Sci & Engn, 4201 Wilson Blvd, Arlington, VA 22230 USA"}, "Rabl, Tilmann": {"WOS": "Univ Toronto, Toronto, ON, Canada"}, "Raj, Pethuru": {"WOS": "Reliance Jio Infocomm Ltd RJIL, Site Reliabil Engn SRE Div, Bangalore, Karnataka, India"}, "Rashid, Mohammed A.": {"WOS": "Massey Univ, Dept Mech & Elect Engn, Auckland 0745, New Zealand"}, "Raveling, Matthew A.": {"WOS": "Mayo Clin, Coll Med, Dept Biochem & Mol Biol, Rochester, MN 55905 USA"}, "Reddy, Akhileshwar": {"WOS": "SRM Univ AP, Comp Sci & Engn, Sch Engn & Sci, Amaravati, Andhra Pradesh, India"}, "Ribeiro, Joao Pedro": {"WOS": "Ctr Hosp Tamega & Sousa, Dept Psychiat & Mental Hlth, Penafiel, Portugal"}, "Rodrigues, Joel J. P. C.": {"WOS": "Natl Inst Telecommun Inatel, Santa Rita Do Sapucai, Brazil"}, "Rossi, Dario": {"WOS": "Telefon Res, Barcelona, Spain"}, "Sa, Filipe": {"WOS": "Univ Coimbra, CISUC Ctr Informat & Syst, Coimbra, Portugal"}, "Sahu, Abhay Sankar": {"WOS": "Univ Kalyani, Dept Geog, Nadia 741235, W Bengal, India"}, "Salomoni, Paola": {"WOS": "Univ Bologna, Dept Comp Sci & Engn, Bologna, Italy"}, "Santos, Gustavo Andre de Araujo": {"WOS": "Sao Paulo State Univ FCAV UNESP, Dept Exact Sci, Via Acesso Prof Paulo Donato Castellane S-N, BR-14884900 Jaboticabal, SP, Brazil"}, "Saravanan, R.": {"WOS": "Vellore Inst Technol, Sch Informat Technol, Vellore 632014, Tamil Nadu, India"}, "Semikalenova, A., I": {"WOS": "Moscow State Law Univ, Moscow, Russia"}, "Shankar, K.": {"WOS": "Alagappa Univ, Dept Comp Applicat, Karaikkudi, Tamil Nadu, India"}, "Sharma, Sanjiv": {"WOS": "MITS Coll, Gwalior, India"}, "Shen, Haiying": {"WOS": "Clemson Univ, Dept Elect & Comp Engn, Clemson, SC 29634 USA"}, "Shen, Tingyan": {"WOS": "Chinese Peoples Liberat Army Gen Hosp, Med Sch, Chinese PLA, Beijing 100853, Peoples R China"}, "Shin, JuHyun": {"WOS": "Chosun Univ, Dept ICT Convergences, Gwangju, South Korea"}, "Shoshani, Arie": {"WOS": "Lawrence Berkeley Lab, Berkeley, CA USA"}, "Shukla, Anupam": {"WOS": "Indian Inst Informat Technol & Management, Gwalior, Madhya Pradesh, India"}, "Simeon, Jerome": {"WOS": "IBM Watson Res, Hawthorne, NY USA"}, "Sokolenko, Liudmyla": {"WOS": "Sumy State Pedag Univ, Dept Business Econ & Adm, Sumy, Ukraine"}, "Song, Baoyan": {"WOS": "Liaoning Univ, Sch Informat, Shenyang 110036, Peoples R China"}, "Sriboonchitta, Songsak": {"WOS": "Univ Balearic Isl, Dept Phys, Palma De Mallorca, Spain"}, "Stathis, Kostas": {"WOS": "Royal Holloway Univ London, Dept Comp Sci, Egham TW20 0EX, Surrey, England"}, "Stepanov, Alexander, V": {"WOS": "Kemerovo State Univ, Fed Budget Educ Inst Higher Educ, Kemerovo 650043, Russia"}, "Stolbovyi, M. I.": {"WOS": "Kharkiv Natl Univ Radio Elect, Dept Informat, Kharkov, Ukraine"}, "Sujith, A. V. L. N.": {"WOS": "SV Engn Coll, Dept CSE, Tirupati, Andhra Prades, India"}, "Sultanov, Rayimbek": {"WOS": "Kahramanmaras Sutcu Imam Univ, Dept Comp Educ & Instruct Technol, Kahramanmaras, Turkey"}, "Sun, Xian-He": {"WOS": "IIT, Dept Comp Sci, 10 West 35th St, Chicago, IL 60616 USA"}, "Sun, Yuezhongyi": {"WOS": "Harbin Med Univ, Dept Endocrinol & Metab, Affiliated Hosp 1, Harbin, Heilongjiang, Peoples R China"}, "Szymanski, L.": {"WOS": "TransEko Design Consulting Off, Warsaw, Poland"}, "Tan Jianrong": {"WOS": "Hangzhou Turbine Machinery Equipment CO LTD, Hangzhou 310022, Peoples R China"}, "Tang, Maolin": {"WOS": "Queensland Univ Technol, Sch Comp Sci, Brisbane, Qld 4000, Australia"}, "Tang, Tao": {"WOS": "Beijing Jiaotong Univ, State Key Lab Traff Control & Safety, Beijing 100044, Peoples R China"}, "Teng, Teng": {"WOS": "Qingdao Acad Intelligent Ind, Qingdao 266109, Shandong, Peoples R China"}, "Tomas, Jesus": {"WOS": "Univ Politecn Valencia, Inst Invest Gest Integrada Zonas Costeras, Valencia, Spain"}, "Toumani, Farouk": {"WOS": "Univ Blaise Pascal, CNRS, LIMOS, UMR CNRS 6158, Clermont Ferrand, France"}, "Tran, Chi": {"WOS": "WM Univ Olsztyn, Fac Geodesy Geospatial & Civil Engn, Olsztyn, Poland"}, "Tzeng, Nian-Feng": {"WOS": "Univ Louisiana, Sch Comp & Informat, Lafayette, LA 70504 USA"}, "Uribeetxeberria, Roberto": {"WOS": "Mondragon Unibertsitatea, Dept Elect & Comp, Goiru 2, Arrasate Mondragon 20500, Spain"}, "Valero, Mateo": {"WOS": "Univ Politecn Cataluna, Barcelona, Spain"}, "van Thiel, G. J.": {"WOS": "Serv Monde, 50 Rue Carnot, F-92284 Suresnes, France"}, "Varun, P. V.": {"WOS": "Indian Inst Sci, Dept Computat & Data Sci, Bangalore, Karnataka, India"}, "Venegas-Martinez, Francisco": {"WOS": "Inst Politecn Nacl, Mexico City, DF, Mexico"}, "Vicente Manjon, Jose": {"WOS": "Univ Politecn Valencia, Inst Univ Tecnol Informac & Comunicac ITACA, Camino Vera S-N, E-46022 Valencia, Spain"}, "Vijayakumar, M.": {"WOS": "Jai Shriram Engn Coll, Tiruppur, India"}, "Vijayakumar, R.": {"WOS": "Mahatma Gandhi Univ, Sch Comp Sci, Kottayam, Kerala, India"}, "Wang, Kuansan": {"WOS": "Microsoft Res, Redmond, WA USA"}, "Wang, Lihua": {"WOS": "Harbin Med Univ, Coll Bioinformat Sci & Technol, Harbin 150081, Peoples R China"}, "Wang, Longde": {"WOS": "Capital Med Univ, Xuanwu Hosp, Dept Neurosurg, Beijing, Peoples R China"}, "Wang, Long-De": {"WOS": "Tongji Univ, Sch Med, Shanghai Tongji Hosp, Dept Intervent Radiol, Shanghai, Peoples R China"}, "Wang, Zhenzhen": {"WOS": "Harbin Med Univ, Affiliated Hosp 4, Dept Cardiol, Harbin 150001, Heilongjiang, Peoples R China"}, "Wittebole, Xavier": {"WOS": "Clin Univ St Luc, Crit Care Dept, Ave Hippocrate 10, B-1200 Brussels, Belgium"}, "Wu, Dan": {"WOS": "Henan Univ Sci & Technol, Sch Math & Stat, Luoyang 471023, Peoples R China"}, "Wu, Xindong": {"WOS": "Mininglamp Software Syst, Beijing, Peoples R China"}, "Xiao, Yun": {"WOS": "Harbin Med Univ, Affiliated Hosp 1, Dept Neurol, Harbin 150001, Heilongjiang, Peoples R China"}, "Xie, Dong": {"WOS": "Chongqing Univ Sci & Technol, Coll Elect & Informat Engn, Chongqing, Peoples R China"}, "Yamaguchi, Atsuko": {"WOS": "CMU, SIB Swiss Inst Bioinformat, Swiss Prot Grp, CH-1211 Geneva 4, Switzerland"}, "Yang, Bo": {"WOS": "Univ Jinan, Shandong Prov Key Lab Network Based Intelligent C, Jinan, Peoples R China"}, "Yang, Jaewon": {"WOS": "Sungkyunkwan Univ, Sch Civil Architectural Engn & Landscape Architec, Nat Sci Campus, Suwan Si, Gyeonggi Do, South Korea"}, "Yang, Weimin": {"WOS": "Jiangsu Vocat Inst Commerce, Sch Trade & Logist, Nanjing 211100, Peoples R China"}, "Yasseri, Taha": {"WOS": "Univ Oxford, Oxford Internet Inst, Oxford, England"}, "Yi, Gangman": {"WOS": "Dongguk Univ, Dept Multimedia Engn, Seoul 04620, South Korea"}, "Yin, Wan-Jian": {"WOS": "Soochow Univ, Soochow Inst Energy & Mat Innovat SIEMIS, Coll Energy, Suzhou 215006, Peoples R China"}, "Yong, Tai-Soon": {"WOS": "Yonsei Univ, Coll Med, Arthropods Med Importance Resource Bank, Dept Environm Med Biol,Inst Trop Med, Seoul, South Korea"}, "Yoon, Seok-Jun": {"WOS": "Korea Univ, Dept Prevent Med, Coll Med, 73 Goryeodae Ro, Seoul 02841, South Korea"}, "Yoon, Seongkyu": {"WOS": "Bristol Myers Squibb, Res & Dev, Princeton, MA USA"}, "Youk, Hyun": {"WOS": "Yonsei Univ, Dept Emergency Med, Wonju Coll Med, 20 Ilsan Ro, Wonju 26426, South Korea"}, "Youm, Sekyoung": {"WOS": "Dongguk Univ, Dept Ind & Syst Engn, 3Ga Pil Dong, Seoul 04620, South Korea"}, "Yu, Qi": {"WOS": "Rochester Inst Technol, Coll Comp & Informat Sci, 102 Lomb Mem Dr, Rochester, NY 14623 USA"}, "Yu, Zeyun": {"WOS": "Univ Wisconsin, Coll Nursing, Milwaukee, WI 53211 USA"}, "Zaniolo, Carlo": {"WOS": "Univ Calif Los Angeles, Los Angeles, CA 90095 USA"}, "Zarochentsev, A.": {"WOS": "Natl Res Ctr, Kurchatov Inst, BigData Lab, Ac Kurchatov Sq, Moscow, Russia"}, "Zhang Yongshun": {"WOS": "Yanshan Univ, Natl Engn Res Ctr Equipment & Technol Cold Strip, Qinhuangdao 066004, Hebei, Peoples R China"}, "Zhang, Guoming": {"WOS": "Shenzhen Eye Hosp, Pediat Retinal Surg Dept, Shenzhen 518040, Peoples R China"}, "Zhang, Ning": {"WOS": "Univ Manchester, Sch Comp Sci, Manchester M13 9PL, Lancs, England"}, "Zhang, Xinzhi": {"WOS": "Hong Kong Baptist Univ, Dept Journalism, Hong Kong, Hong Kong, Peoples R China"}, "Zhang, Xuyun": {"WOS": "Univ Technol Sydney, Fac Engn & IT, Sydney, NSW 2007, Australia"}, "Zhang, Yunpeng_0": {"WOS": "Harbin Med Univ, Coll Bioinformat Sci & Technol, Harbin 150081, Heilongjiang, Peoples R China"}, "Zhang, Yunpeng_1": {"WOS": "Univ Elect Sci & Technol China, Ctr Informat Biol, Chengdu 611731, Peoples R China"}, "Zheng, B.": {"WOS": "Zhejiang Univ Hangzhou, Dept Phys, Hangzhou 310027, Peoples R China"}, "Zhou, Meng": {"WOS": "Harbin Inst Technol, Sch Life Sci & Technol, Harbin 150001, Peoples R China"}, "Zuo, Wangda": {"WOS": "Univ Colorado, Boulder, CO 80309 USA"}}